{
  "questions": [
    {
      "stage": "pre",
      "question": "文科生在AI时代最大的资产是什么？",
      "options": [
        "编程能力",
        "数据分析能力",
        "文字感知力、叙事能力、社会洞察——这些是AI做不到但可以杠杆放大的",
        "记忆力"
      ],
      "correct": 2,
      "explanation": "文科生的核心资产不是技术能力，而是AI做不到的东西：文字感知力（知道什么是好的文字）、叙事能力（能把事情讲清楚打动人）、社会洞察（对人、对组织、对社会的理解）。这些加上AI工具，可以杠杆放大。"
    },
    {
      "stage": "post",
      "question": "你现在处于哪个阶段，你打算怎么开始下一步？",
      "options": [
        "还没开始，先从认知重建开始",
        "在校/准备求职，重点做作品集和简历",
        "马上入职，重点做入职生存和第一篇内容",
        "已经在职，重点做成果档案和判断力升级"
      ],
      "correct": 2,
      "explanation": "这是路线图的自检问题。不同阶段有不同的优先事项：认知重建→作品集→求职→职场扎根→持续进化。知道自己现在在哪，才能找到下一步最应该做的事。"
    }
  ]
}
